opentelemetry/exporter/cloud_trace/__init__.py
opentelemetry/exporter/cloud_trace/cloud_trace_propagator.py
opentelemetry/exporter/cloud_trace/version.py
opentelemetry_exporter_cloud_trace-0.10b1.dist-info/METADATA
opentelemetry_exporter_cloud_trace-0.10b1.dist-info/WHEEL
opentelemetry_exporter_cloud_trace-0.10b1.dist-info/top_level.txt
opentelemetry_exporter_cloud_trace-0.10b1.dist-info/RECORD
